{
    "backend": "flask",
    "db_name": "",
    "db_pass": "",
    "db_type": "sqlite",
    "db_user": "",
    "dbms": "1",
    "description": "generated product",
    "design": "material-kit",
    "docker": "1",
    "err_code": 0,
    "frontend": "",
    "heroku": "0",
    "pattern": "mvc",
    "pro": "0",
    "task_id": "56aaf7f9-e185-499f-9eb9-c8d9b63b6191",
    "task_info": "Upload Sources [0%] - 349 files",
    "task_output": "56aaf7f9-e185-499f-9eb9-c8d9b63b6191.zip",
    "task_result": "SUCCESS",
    "task_state": "RUNNING",
    "task_ts_end": "2023-06-23-12-04-54",
    "task_ts_start": "2023-06-23-12-04-52"
}